.bumpversion.cfg
.coveragerc
.editorconfig
.pycheckrc
CHANGES.rst
LICENSE
MANIFEST.in
PROJECT_INFO.rst
README.rst
VERSION.txt
behave.ini
pylintrc
setup.cfg
setup.py
setuptools_behave.py
tox.ini
behave/__init__.py
behave/__main__.py
behave/_types.py
behave/configuration.py
behave/i18n.py
behave/importer.py
behave/json_parser.py
behave/log_capture.py
behave/matchers.py
behave/model.py
behave/model_describe.py
behave/parser.py
behave/runner.py
behave/runner_util.py
behave/step_registry.py
behave/tag_expression.py
behave/tag_matcher.py
behave/textutil.py
behave/userdata.py
behave/compat/__init__.py
behave/compat/collections.py
behave/compat/importlib.py
behave/compat/os_path.py
behave/formatter/__init__.py
behave/formatter/ansi_escapes.py
behave/formatter/base.py
behave/formatter/filter_formatter.py
behave/formatter/filters.py
behave/formatter/formatters.py
behave/formatter/json.py
behave/formatter/null.py
behave/formatter/plain.py
behave/formatter/pretty.py
behave/formatter/progress.py
behave/formatter/rerun.py
behave/formatter/sphinx_steps.py
behave/formatter/sphinx_util.py
behave/formatter/steps.py
behave/formatter/tags.py
behave/reporter/__init__.py
behave/reporter/base.py
behave/reporter/junit.py
behave/reporter/summary.py
behave4cmd0/__all_steps__.py
behave4cmd0/__init__.py
behave4cmd0/__setup.py
behave4cmd0/command_shell.py
behave4cmd0/command_steps.py
behave4cmd0/command_util.py
behave4cmd0/failing_steps.py
behave4cmd0/note_steps.py
behave4cmd0/passing_steps.py
behave4cmd0/pathutil.py
behave4cmd0/textutil.py
behave4cmd0/log/__init__.py
behave4cmd0/log/steps.py
behave_py3.egg-info/PKG-INFO
behave_py3.egg-info/SOURCES.txt
behave_py3.egg-info/dependency_links.txt
behave_py3.egg-info/entry_points.txt
behave_py3.egg-info/requires.txt
behave_py3.egg-info/top_level.txt
behave_py3.egg-info/zip-safe
bin/behave
bin/behave.cmd
bin/behave.step_durations.py
bin/json.format.py
bin/jsonschema_validate.py
bin/make_localpi.py
bin/project_bootstrap.sh
bin/toxcmd.py
bin/toxcmd3.py
docs/Makefile
docs/api.rst
docs/appendix.rst
docs/behave.rst
docs/behave.rst-template
docs/behave_ecosystem.rst
docs/comparison.rst
docs/conf.py
docs/context_attributes.rst
docs/django.rst
docs/formatters.rst
docs/gherkin.rst
